dash_rjsf/DashRjsf.py
dash_rjsf/__init__.py
dash_rjsf/_imports_.py
dash_rjsf/dash_rjsf.min.js
dash_rjsf/dash_rjsf.min.js.map
dash_rjsf/metadata.json
dash_rjsf/package-info.json
dash_rjsf-0.0.4.dist-info/LICENSE
dash_rjsf-0.0.4.dist-info/METADATA
dash_rjsf-0.0.4.dist-info/WHEEL
dash_rjsf-0.0.4.dist-info/top_level.txt
dash_rjsf-0.0.4.dist-info/RECORD
