Metadata-Version: 2.1
Name: dash-rjsf
Version: 0.0.4
Summary: Dash component based on the react-jsonschema-form
Home-page: https://github.com/alhoo/dash_rjsf
Author: Lasse Hyyrynen <lasse.hyyrynen@anomalia.io>
License: MIT
Platform: UNKNOWN
Classifier: Framework :: Dash
License-File: LICENSE
